darkdisplay/__init__.py
darkdisplay/notification.py
darkdisplay/overlay.py
darkdisplay-0.0.9.dist-info/LICENSE
darkdisplay-0.0.9.dist-info/METADATA
darkdisplay-0.0.9.dist-info/WHEEL
darkdisplay-0.0.9.dist-info/top_level.txt
darkdisplay-0.0.9.dist-info/RECORD
