Metadata-Version: 2.1
Name: darkdisplay
Version: 0.0.9
Summary: A package to display a notification or overlay
Author-email: Dark_Eden <darkedenc9@gmail.com>
Project-URL: Homepage, https://github.com/DarkEden-coding/darkdisplay
Project-URL: Bug Tracker, https://github.com/DarkEden-coding/darkdisplay/issues
Classifier: Programming Language :: Python :: 3
Classifier: License :: OSI Approved :: MIT License
Classifier: Operating System :: OS Independent
Requires-Python: >=3.7
License-File: LICENSE
